VenomLearn/__init__.py
VenomLearn/__main__.py
VenomLearn/config.py
VenomLearn/main.py
VenomLearn/topics/__init__.py
VenomLearn/topics/advanced.py
VenomLearn/topics/basics.py
VenomLearn/topics/control_flow.py
VenomLearn/topics/data_structures.py
VenomLearn/topics/functions.py
VenomLearn/topics/modules.py
VenomLearn/topics/oop.py
VenomLearn/utils/__init__.py
VenomLearn/utils/checker.py
VenomLearn/utils/progress_tracker.py
VenomLearn/utils/terminal_ui.py
VenomLearn-0.1.3.dist-info/METADATA
VenomLearn-0.1.3.dist-info/WHEEL
VenomLearn-0.1.3.dist-info/entry_points.txt
VenomLearn-0.1.3.dist-info/top_level.txt
VenomLearn-0.1.3.dist-info/RECORD
