Metadata-Version: 2.2
Name: VenomLearn
Version: 0.1.3
Summary: An interactive Python learning package
Home-page: https://github.com/VenomLearn/VenomLearn
Author: VenomLearn Team
Author-email: example@example.com
Keywords: python,learning,interactive,education
Classifier: Development Status :: 3 - Alpha
Classifier: Intended Audience :: Education
Classifier: License :: OSI Approved :: MIT License
Classifier: Programming Language :: Python :: 3
Classifier: Programming Language :: Python :: 3.7
Classifier: Programming Language :: Python :: 3.8
Classifier: Programming Language :: Python :: 3.9
Requires-Dist: rich
Requires-Dist: questionary
Requires-Dist: pyfiglet
Requires-Dist: tqdm
Dynamic: author
Dynamic: author-email
Dynamic: classifier
Dynamic: description
Dynamic: description-content-type
Dynamic: home-page
Dynamic: keywords
Dynamic: requires-dist
Dynamic: summary
